dbt/adapters/sqlite/__init__.py
dbt/adapters/sqlite/__version__.py
dbt/adapters/sqlite/connections.py
dbt/adapters/sqlite/impl.py
dbt/adapters/sqlite/relation.py
dbt/include/sqlite/__init__.py
dbt/include/sqlite/dbt_project.yml
dbt/include/sqlite/sample_profiles.yml
dbt/include/sqlite/macros/adapters.sql
dbt/include/sqlite/macros/catalog.sql
dbt/include/sqlite/macros/core_overrides.sql
dbt/include/sqlite/macros/materializations/test.sql
dbt/include/sqlite/macros/materializations/incremental/incremental.sql
dbt/include/sqlite/macros/materializations/seed/helpers.sql
dbt/include/sqlite/macros/materializations/seed/seed.sql
dbt/include/sqlite/macros/materializations/snapshot/snapshot_merge.sql
dbt/include/sqlite/macros/materializations/snapshot/strategies.sql
dbt/include/sqlite/macros/materializations/table/table.sql
dbt/include/sqlite/macros/materializations/view/view.sql
dbt/include/sqlite/macros/utils/any_value.sql
dbt/include/sqlite/macros/utils/bool_or.sql
dbt/include/sqlite/macros/utils/cast_bool_to_text.sql
dbt/include/sqlite/macros/utils/dateadd.sql
dbt/include/sqlite/macros/utils/datediff.sql
dbt/include/sqlite/macros/utils/hash.sql
dbt/include/sqlite/macros/utils/position.sql
dbt/include/sqlite/macros/utils/right.sql
dbt/include/sqlite/macros/utils/timestamps.sql
dbt_sqlite-1.9.0.dist-info/LICENSE.txt
dbt_sqlite-1.9.0.dist-info/METADATA
dbt_sqlite-1.9.0.dist-info/WHEEL
dbt_sqlite-1.9.0.dist-info/top_level.txt
dbt_sqlite-1.9.0.dist-info/RECORD
